rcfdtdpy/__init__.py
rcfdtdpy/sim.py
rcfdtdpy-0.2.6.dist-info/METADATA
rcfdtdpy-0.2.6.dist-info/RECORD
rcfdtdpy-0.2.6.dist-info/WHEEL
rcfdtdpy-0.2.6.dist-info/top_level.txt
